herostools/__init__.py
herostools/helper.py
herostools/actor/__init__.py
herostools/actor/data_archiver.py
herostools/actor/prometheus.py
herostools/actor/statemachine.py
herostools-0.4.1.dist-info/METADATA
herostools-0.4.1.dist-info/WHEEL
herostools-0.4.1.dist-info/licenses/LICENSE
herostools-0.4.1.dist-info/licenses/LICENSE.LESSER
herostools-0.4.1.dist-info/RECORD
